{
  "dialogues": [
    {
      "character": "",
      "hideCharacter": true,
      "text": "──3ヶ月後。\n整体院は順調に経営を続けていた。"
    },
    {
      "character": "",
      "hideCharacter": true,
      "text": "しかし、売上の大半は、ショップでの買い物に消えていた…。",
      "playSE": "shop_door"
    },
    {
      "character": "店員",
      "expression": "face_smile_01",
      "text": "お客様、今日もいらっしゃいませ♡",
      "characterImage": "clerk/clerk.png"
    },
    {
      "character": "player",
      "hideCharacter": true,
      "text": "（また来てしまった…今日は何を買おうか…）"
    },
    {
      "character": "店員",
      "expression": "face_pleased_01",
      "text": "お客様の累計購入額、ついに500万円を超えましたよ♡"
    },
    {
      "character": "player",
      "hideCharacter": true,
      "text": "ご、500万！？そんなに使ってたのか…"
    },
    {
      "character": "店員",
      "expression": "face_smile_01",
      "text": "ふふっ♡ 素晴らしいですね♡"
    },
    {
      "character": "店員",
      "expression": "face_pleased_01",
      "text": "実は…お客様にお願いがあるんです♡"
    },
    {
      "character": "player",
      "hideCharacter": true,
      "text": "お、お願い？"
    },
    {
      "character": "店員",
      "expression": "face_pleased_01",
      "text": "開発中の試作品を、お客様で試させていただけませんか？♡"
    },
    {
      "character": "店員",
      "expression": "face_horny_01",
      "text": "もちろん、VIPサービスよりもっと過激なこともしちゃいます…♡"
    },
    {
      "character": "",
      "hideCharacter": true,
      "text": "──それから、{{playerName}}は店員の実験台となった。"
    },
    {
      "character": "店員",
      "expression": "face_smile_01",
      "text": "今日は新型の媚薬オイルです♡"
    },
    {
      "character": "店員",
      "expression": "face_pleased_01",
      "text": "塗った瞬間から全身が性感帯になるという…♡"
    },
    {
      "character": "店員",
      "expression": "face_horny_01",
      "text": "まず私が自分の体に塗って、それからお客様に塗ってあげますね♡"
    },
    {
      "character": "",
      "hideCharacter": true,
      "text": "店員は服を脱ぎ、オイルを全身に塗り始めた。"
    },
    {
      "character": "店員",
      "expression": "face_horny_01",
      "text": "んっ…♡ すごい…本当に全身が敏感に…♡"
    },
    {
      "character": "店員",
      "expression": "face_horny_01",
      "text": "おっぱいにもたっぷり…♡"
    },
    {
      "character": "店員",
      "expression": "face_horny_01",
      "text": "ん…♡ 乳首が…ビンビンになっちゃいました♡"
    },
    {
      "character": "店員",
      "expression": "face_horny_01",
      "text": "おまんこにも…あぁっ♡ クリトリスが…♡"
    },
    {
      "character": "player",
      "hideCharacter": true,
      "text": "（す、すごい光景だ…）"
    },
    {
      "character": "店員",
      "expression": "face_pleased_01",
      "text": "では、お客様…♡"
    },
    {
      "character": "店員",
      "expression": "face_horny_01",
      "text": "私のおっぱいで、オイルを塗ってあげますね♡"
    },
    {
      "character": "",
      "hideCharacter": true,
      "text": "店員は自分の胸を{{playerName}}の体に押し付け、オイルを塗り広げていく。"
    },
    {
      "character": "店員",
      "expression": "face_horny_01",
      "text": "ほら…私の乳首も硬くなってるの分かります？♡"
    },
    {
      "character": "player",
      "hideCharacter": true,
      "text": "うわあああ！すごい！体中が…！"
    },
    {
      "character": "店員",
      "expression": "face_horny_01",
      "text": "下半身は…おまんこで塗ってあげますね♡"
    },
    {
      "character": "",
      "hideCharacter": true,
      "text": "店員は{{playerName}}の上にまたがり、濡れた秘部を擦り付けながらオイルを塗っていく。"
    },
    {
      "character": "店員",
      "expression": "face_horny_01",
      "text": "あぁ♡ お客様のおちんちんに、私の愛液とオイルが…♡"
    },
    {
      "character": "player",
      "hideCharacter": true,
      "text": "ううっ！"
    },
    {
      "character": "店員",
      "expression": "face_pleased_01",
      "text": "ふふっ♡ 反応もバッチリですね♡"
    },
    {
      "character": "店員",
      "expression": "face_smile_01",
      "text": "データも取れましたし、これなら商品化できそうです♡"
    },
    {
      "character": "",
      "hideCharacter": true,
      "text": "──また別の日"
    },
    {
      "character": "店員",
      "expression": "face_pleased_01",
      "text": "今日は電動式の新型器具を…♡"
    },
    {
      "character": "店員",
      "expression": "face_horny_01",
      "text": "お客様のおちんちんに装着して、データを取らせてください♡"
    },
    {
      "character": "player",
      "hideCharacter": true,
      "text": "（もう何でも来い…！）"
    },
    {
      "character": "",
      "hideCharacter": true,
      "text": "{{playerName}}は完全に店員の実験体と化していた。"
    },
    {
      "character": "",
      "hideCharacter": true,
      "text": "しかし、過激な新商品を誰よりも早く体験できることに、\n奇妙な満足感を覚えていた。"
    },
    {
      "character": "店員",
      "expression": "face_pleased_01",
      "text": "お客様のおかげで、素晴らしい商品が次々と開発できています♡"
    },
    {
      "character": "店員",
      "expression": "face_smile_01",
      "text": "これからも末永く…私のモニターでいてくださいね…♡"
    },
    {
      "character": "店員",
      "expression": "face_horny_01",
      "text": "次はもっとすごいの用意しますから♡"
    },
    {
      "character": "player",
      "hideCharacter": true,
      "text": "はい！楽しみにしてます！"
    },
    {
      "character": "",
      "hideCharacter": true,
      "text": "整体師として成功するはずが、\nいつの間にかアダルトグッズの実験体になってしまった。"
    },
    {
      "character": "",
      "hideCharacter": true,
      "text": "でも、これはこれで幸せなのかもしれない。",
      "triggerEnding": "shop"
    },
    {
      "character": "",
      "hideCharacter": true,
      "text": "【SHOP END - 店員さんのモニターEND】",
      "triggerEnding": "shop"
    }
  ]
}