[
  {
    "id": "gift_flowers",
    "name": "花束",
    "description": "可爱的花束。送给别人一定会很开心。",
    "price": 3000,
    "category": "gift",
    "effect": { "type": "trust_boost", "value": 2, "duration": "instant" },
    "icon": "gift_flowers.png",
    "isTrialOnly": true,
    "stock": 1,
    "unlockDay": 1,
    "rating": 4.5,
    "reviews": [
      { "user": "温柔的人", "rating": 5, "comment": "女性果然喜欢花呢。对方非常开心！" },
      { "user": "送礼新手", "rating": 4, "comment": "虽然是经典之选但绝不会出错。可以放心赠送。" },
      { "user": "爱花人士", "rating": 5, "comment": "香气宜人，外观也很可爱。能看到对方的笑容真开心。" },
      { "user": "浪漫主义者", "rating": 4, "comment": "能传达出小小的关心。有助于增进感情。" }
    ]
  },
  {
    "id": "gift_matcha_chocolate",
    "name": "京都宇治抹茶生巧克力",
    "description": "奢侈地使用了老字号茶铺的最高级宇治抹茶。入口即化，抹茶香气浓郁。",
    "price": 7000,
    "category": "gift",
    "effect": { "type": "trust_boost", "value": 3, "duration": "instant" },
    "icon": "gift_matcha_chocolate.png",
    "isTrialOnly": true,
    "stock": 1,
    "unlockDay": 1,
    "rating": 4.8,
    "reviews": [
      { "user": "抹茶爱好者", "rating": 5, "comment": "抹茶的香气非常正宗！高级感十足，非常适合送礼。" },
      { "user": "和果子控", "rating": 5, "comment": "不会太甜，成熟的味道。抹茶控无法抗拒。" },
      { "user": "京都通", "rating": 5, "comment": "仿佛置身京都的高雅味道。包装也很精美。" },
      { "user": "选礼达人", "rating": 4, "comment": "和洋融合的绝妙平衡。适合送给特别的人。" }
    ]
  },
  {
    "id": "gift_teddy_bear",
    "name": "毛绒玩偶",
    "description": "毛茸茸的可爱小熊玩偶。抱着它会感到无比安心。",
    "price": 4000,
    "category": "gift",
    "effect": { "type": "trust_boost", "value": 2, "duration": "instant" },
    "icon": "gift_teddy_bear.png",
    "isTrialOnly": true,
    "stock": 1,
    "unlockDay": 1,
    "rating": 4.6,
    "reviews": [
      { "user": "治愈系爱好者", "rating": 5, "comment": "毛茸茸的太棒了！每晚抱着睡。" },
      { "user": "送礼高手", "rating": 5, "comment": "女孩子都喜欢毛绒玩偶。绝对不会出错的礼物。" },
      { "user": "新手", "rating": 4, "comment": "作为第一件礼物送出去了。对方非常开心。" },
      { "user": "玩偶收藏家", "rating": 5, "comment": "小熊的表情太可爱了！放在房间里也很治愈。" }
    ]
  },
  {
    "id": "gift_eye_mask",
    "name": "眼罩",
    "description": "设计可爱的眼罩。温柔呵护疲劳的双眼。带有薰衣草香味。",
    "price": 3000,
    "category": "gift",
    "effect": { "type": "trust_boost", "value": 2, "duration": "instant" },
    "icon": "gift_eye_mask.png",
    "isTrialOnly": true,
    "stock": 1,
    "unlockDay": 2,
    "rating": 4.5,
    "reviews": [
      { "user": "工作疲惫", "rating": 5, "comment": "缓解了眼部疲劳很舒适！设计也很可爱，很喜欢。" },
      { "user": "改善睡眠", "rating": 4, "comment": "睡眠质量提高了。香味也很好。" },
      { "user": "送礼新手", "rating": 5, "comment": "实用又受欢迎的礼物。" },
      { "user": "护眼达人", "rating": 4, "comment": "佩戴感很好，眼睛轻松多了。非常适合作为礼物。" }
    ]
  },
  {
    "id": "gift_aroma_diffuser",
    "name": "香薰机",
    "description": "在房间里散发温和香气的香薰机。放松效果极佳，能治愈工作的疲劳。",
    "price": 20000,
    "category": "gift",
    "effect": { "type": "trust_boost", "value": 4, "duration": "instant" },
    "icon": "gift_aroma_diffuser.png",
    "isTrialOnly": true,
    "stock": 1,
    "unlockDay": 3,
    "rating": 4.8,
    "reviews": [
      { "user": "香薰爱好者", "rating": 5, "comment": "整个房间都弥漫着好闻的香味！工作专注力也提升了。" },
      { "user": "注重放松", "rating": 5, "comment": "缓解压力的最佳选择。每天都在用。" },
      { "user": "选礼达人", "rating": 4, "comment": "实用又时尚。非常适合送给女性。" },
      { "user": "健康达人", "rating": 5, "comment": "支持天然精油所以很放心。睡眠质量也提升了。" }
    ]
  },
  {
    "id": "gift_neck_pillow",
    "name": "温热颈枕",
    "description": "缓缓温热的电动颈枕。能舒缓肩膀和颈部的僵硬。",
    "price": 5000,
    "category": "gift",
    "effect": { "type": "trust_boost", "value": 2, "duration": "instant" },
    "icon": "gift_neck_pillow.png",
    "isTrialOnly": true,
    "stock": 1,
    "unlockDay": 1,
    "rating": 4.7,
    "reviews": [
      { "user": "办公族", "rating": 5, "comment": "工作时使用。温温的太舒服了。肩膀轻松多了。" },
      { "user": "肩膀酸痛", "rating": 5, "comment": "去整体院之间的自我护理。温热感很舒服。" },
      { "user": "选礼达人", "rating": 4, "comment": "送给肩膀酸痛的人最合适。实用又受欢迎。" },
      { "user": "回购客", "rating": 5, "comment": "买了第二个。家里和办公室各一个。离不开了。" }
    ]
  },
  {
    "id": "gift_whiskey",
    "name": "高级威士忌",
    "description": "苏格兰产单一麦芽。25年陈酿的琥珀色液体沁入疲惫的身体。",
    "price": 18000,
    "category": "gift",
    "effect": { "type": "trust_boost", "value": 4, "duration": "instant" },
    "icon": "gift_whiskey.png",
    "isTrialOnly": true,
    "stock": 1,
    "unlockDay": 3,
    "rating": 4.9,
    "reviews": [
      { "user": "威士忌行家", "rating": 5, "comment": "25年麦芽的深度无与伦比。纯饮时是至福时刻。" },
      { "user": "调酒师", "rating": 5, "comment": "我们店也有卖。送给爱酒之人绝不会出错。" },
      { "user": "晚酌派", "rating": 5, "comment": "下班后的一杯换成这个后每天都很幸福。" },
      { "user": "礼物购买者", "rating": 4, "comment": "送给了爱喝酒的上司。得到了『你很懂嘛』的高评价。" }
    ]
  },
  {
    "id": "gift_luxury_bag",
    "name": "高级品牌包",
    "description": "著名高级品牌的限定款包包。",
    "price": 500000,
    "category": "gift",
    "effect": { "type": "trust_boost", "value": 10, "duration": "instant" },
    "icon": "gift_luxury_bag.png",
    "isTrialOnly": true,
    "stock": 1,
    "unlockDay": 8,
    "rating": 5.0,
    "reviews": [
      { "user": "亿万富翁", "rating": 5, "comment": "金钱买不到爱情，但这个或许另当别论……？" },
      { "user": "借钱购买", "rating": 5, "comment": "倾尽全部财产买的。不后悔！" },
      { "user": "品牌控", "rating": 5, "comment": "没想到真的在卖……能买到的人真令人羡慕。" },
      { "user": "段子购买者", "rating": 5, "comment": "当个话题倒是不错。至于值不值这个价……？" }
    ]
  },
  {
    "id": "gift_diamond_ring",
    "name": "钻石戒指",
    "description": "最高级钻石戒指。誓约永恒之爱的终极礼物。",
    "price": 5000000,
    "category": "gift",
    "effect": { "type": "trust_boost", "value": 20, "duration": "instant" },
    "icon": "gift_diamond_ring.png",
    "isTrialOnly": false,
    "stock": 1,
    "unlockDay": 10,
    "rating": 5.0,
    "reviews": [
      { "user": "珠宝收藏家", "rating": 5, "comment": "铂金底座配以完美切工。一生一世的戒指。" },
      { "user": "名流", "rating": 5, "comment": "平时也经常看钻石，但这个品质是真品。" },
      { "user": "未婚夫", "rating": 5, "comment": "为求婚购买。完美贴合她的无名指。" },
      { "user": "富豪", "rating": 5, "comment": "物有所值的逸品。送给重要之人的最佳礼物。" }
    ]
  },
  {
    "id": "gift_luxury_watch",
    "name": "高级腕表",
    "description": "瑞士品牌的最高级腕表。镶嵌钻石的表盘闪闪发光。",
    "price": 1000000,
    "category": "gift",
    "effect": { "type": "trust_boost", "value": 25, "duration": "instant" },
    "icon": "gift_luxury_watch.png",
    "isTrialOnly": false,
    "stock": 1,
    "unlockDay": 9,
    "rating": 5.0,
    "reviews": [
      { "user": "手表发烧友", "rating": 5, "comment": "机芯精度超凡入圣。拥有它就是一种喜悦。" },
      { "user": "企业家", "rating": 5, "comment": "在商务场合也能让人刮目相看。作为投资也很优秀。" },
      { "user": "收藏家", "rating": 5, "comment": "正因为是限量版才有价值。想珍藏一生的一件。" },
      { "user": "名媛", "rating": 5, "comment": "丈夫送的礼物。每次戴上都感到幸福。" }
    ]
  },
  {
    "id": "gift_luxury_car",
    "name": "高级跑车",
    "description": "意大利产高级跑车。漆黑的车身配上真红色真皮座椅。最高时速330km。",
    "price": 10000000,
    "category": "gift",
    "effect": { "type": "trust_boost", "value": 30, "duration": "instant" },
    "icon": "gift_luxury_car.png",
    "isTrialOnly": false,
    "stock": 1,
    "unlockDay": 11,
    "rating": 5.0,
    "reviews": [
      { "user": "汽车发烧友", "rating": 5, "comment": "光是发动机的声音就让人起鸡皮疙瘩。人生最棒的购物。" },
      { "user": "周末飙车族", "rating": 5, "comment": "在高速上踩油门那一刻的加速感无法言喻。" },
      { "user": "石油大亨", "rating": 5, "comment": "车库里的第十辆。这个品牌从来不会让人失望。" },
      { "user": "实现梦想的人", "rating": 5, "comment": "从小就有的梦想。每次握住方向盘都想落泪。" }
    ]
  },
  {
    "id": "gift_black_lingerie",
    "name": "黑色蕾丝内衣套装",
    "description": "若隐若现的性感设计。穿上就让人心跳加速。",
    "price": 10000,
    "category": "gift",
    "effect": { "type": "mixed_effect", "developValue": 4, "duration": "instant" },
    "icon": "gift_black_lingerie.png",
    "isTrialOnly": true,
    "stock": 1,
    "unlockDay": 5,
    "rating": 4.9,
    "reviews": [
      { "user": "成熟女性", "rating": 5, "comment": "穿上这个的话……会变得奇怪的。" },
      { "user": "内衣爱好者", "rating": 5, "comment": "质量好，设计也棒。适合特别的日子。" },
      { "user": "初次购买", "rating": 4, "comment": "虽然害羞……但有种想穿穿看的魅力。" },
      { "user": "必定回购", "rating": 5, "comment": "他也很开心。买对了！" }
    ],
    "unlockCondition": { "developLevel": 3 }
  },
  {
    "id": "gift_hemp_rope",
    "name": "麻绳套装",
    "description": "上等麻绳捆绑套装。柔软的处理适合初学者使用。",
    "price": 30000,
    "category": "gift",
    "effect": { "type": "mixed_effect", "developValue": 4, "duration": "instant" },
    "icon": "gift_hemp_rope.png",
    "isTrialOnly": true,
    "stock": 1,
    "unlockDay": 5,
    "rating": 4.6,
    "reviews": [
      { "user": "绳师", "rating": 5, "comment": "这麻绳的质量很棒。贴肤柔软，不易留痕。" },
      { "user": "情侣", "rating": 4, "comment": "两个人一起尝试了。感觉打开了新世界的大门……" },
      { "user": "初学者", "rating": 5, "comment": "附带说明书很方便。虽然一开始很害羞，但感觉要入坑了。" },
      { "user": "回购客", "rating": 5, "comment": "第三套了。越用越顺手。伴侣也很喜欢。" }
    ],
    "unlockCondition": { "developLevel": 4 }
  },
  {
    "id": "gift_pink_rotor",
    "name": "粉色跳蛋",
    "description": "可爱粉色的小型振动器。静音设计，自慰必备。",
    "price": 10000,
    "category": "gift",
    "effect": { "type": "mixed_effect", "developValue": 5, "duration": "instant" },
    "icon": "gift_pink_rotor.png",
    "isTrialOnly": true,
    "stock": 1,
    "unlockDay": 5,
    "rating": 4.7,
    "reviews": [
      { "user": "自慰新手", "rating": 5, "comment": "作为第一个小玩具太合适了！小豆豆被刺激得好舒服♡" },
      { "user": "每晚必用", "rating": 5, "comment": "没有它已经睡不着了……♡" },
      { "user": "敏感女子", "rating": 4, "comment": "太强了马上就去了……最弱档也刺激太大♡" },
      { "user": "跳蛋爱好者", "rating": 5, "comment": "乳头和小豆豆都能用！泡澡时也能用很方便♡" }
    ],
    "unlockCondition": { "developLevel": 5 }
  },
  {
    "id": "gift_vibrator",
    "name": "电动按摩棒",
    "description": "强力振动的电动按摩棒。全身都能用，但碰到敏感部位就是秒高潮的威力。",
    "price": 25000,
    "category": "gift",
    "effect": { "type": "mixed_effect", "developValue": 6, "duration": "instant" },
    "icon": "gift_vibrator.png",
    "isTrialOnly": true,
    "stock": 1,
    "unlockDay": 5,
    "rating": 4.9,
    "reviews": [
      { "user": "电动按摩棒初体验", "rating": 5, "comment": "振动太强腰都要散了……但停不下来♡" },
      { "user": "老手", "rating": 5, "comment": "跳蛋完全没法比的威力。已经离不开了♡" },
      { "user": "全身使用", "rating": 5, "comment": "不光是小豆豆，乳头和大腿也能用太棒了♡" },
      { "user": "自慰爱好者", "rating": 4, "comment": "声音有点大，但效果超群。买对了♡" },
      { "user": "开发敏感度中", "rating": 5, "comment": "用这个开发之后普通的那个已经满足不了了……♡" }
    ],
    "unlockCondition": { "developLevel": 6 }
  },
  {
    "id": "gift_massage_av",
    "name": "AV『无仁义施术 ～堕落于整体师的大姐～』",
    "description": "在黑道中令人闻风丧胆的大姐，无法抗拒整体师的手法而堕落的话题之作。系列累计销量第一。",
    "price": 12000,
    "category": "gift",
    "effect": { "type": "mixed_effect", "developValue": 6, "duration": "instant" },
    "icon": "gift_massage_av.png",
    "isTrialOnly": true,
    "stock": 1,
    "unlockDay": 5,
    "rating": 4.8,
    "reviews": [
      { "user": "系列粉丝", "rating": 5, "comment": "大姐逐渐堕落的演出太精彩了。系列最高杰作。" },
      { "user": "全卷购入者", "rating": 5, "comment": "Vol.1的『组长情妇篇』也不错，但这部最能撸。" },
      { "user": "黑帮电影爱好者", "rating": 4, "comment": "作为黑帮片完成度也很高。不看色情部分也能看的品质。" },
      { "user": "狂热粉", "rating": 5, "comment": "中段大姐嘴上说着『……住手』腰却在动的那个镜头让我确信。神作。" }
    ],
    "unlockCondition": { "developLevel": 7 }
  },
  {
    "id": "gift_custom_dildo",
    "name": "整体师定制假阳具",
    "description": "完全复制整体师的形状的特大假阳具。从龟头形状到血管的浮起都忠实再现。在家也能体验被顶到深处的快感。",
    "price": 50000,
    "category": "gift",
    "effect": { "type": "mixed_effect", "developValue": 7, "duration": "instant" },
    "icon": "gift_custom_dildo.png",
    "isTrialOnly": true,
    "stock": 1,
    "unlockDay": 5,
    "unlockCondition": { "developLevel": 9 }
  }
]
