{
  "dialogues": [
    {
      "character": "",
      "hideCharacter": true,
      "text": "──11週目の朝。\nタツ姐の身体は、もはや施術なしでは日常生活に支障をきたすレベルになっていた。"
    },
    {
      "character": "player",
      "hideCharacter": true,
      "text": "（11週目…もうすぐ3ヶ月だな。タツ姐、完全に俺なしじゃ生きていけない身体になってる。）"
    },
    {
      "character": "player",
      "hideCharacter": true,
      "text": "（おかげで経営も安定してきた…全部タツ姐のおかげだ。）"
    },
    {
      "include": "common/weekly_settlement"
    },
    {
      "character": "",
      "hideCharacter": true,
      "text": "",
      "playSE": "door_chime"
    },
    {
      "character": "タツ姐",
      "expression": "angry",
      "text": "…おう。",
      "outfit": "suit"
    },
    {
      "character": "player",
      "expression": "closemouth",
      "text": "タツ姐さん！ …って、なんか機嫌悪そうですね。"
    },
    {
      "character": "タツ姐",
      "expression": "angry",
      "text": "…ああ。お前のせいだ。",
      "outfit": "suit"
    },
    {
      "character": "player",
      "expression": "closemouth",
      "text": "え？ 俺のせい？"
    },
    {
      "character": "タツ姐",
      "expression": "shy",
      "text": "…この前よ。部下シメてる最中に…お前の施術思い出しちまった。",
      "outfit": "suit"
    },
    {
      "character": "player",
      "expression": "closemouth",
      "text": "シメてる最中に…？"
    },
    {
      "character": "タツ姐",
      "expression": "angry",
      "text": "ああ。そしたら…手が…甘くなっちまった。",
      "outfit": "suit"
    },
    {
      "character": "タツ姐",
      "expression": "shy",
      "text": "部下に『姐さん、今日は優しいっスね』とか言われてよ…。殺すぞ。",
      "outfit": "suit"
    },
    {
      "character": "player",
      "text": "（シメが甘くなるって…どんだけ施術のこと考えてるんだ…。）"
    },
    {
      "character": "タツ姐",
      "expression": "angry",
      "text": "闇金の社長が、仕事中にそんなこと考えてんじゃねぇよな…クソ…。",
      "outfit": "suit"
    },
    {
      "character": "player",
      "expression": "closemouth",
      "text": "それだけ俺の施術が効いてるってことですね。"
    },
    {
      "character": "タツ姐",
      "expression": "shy",
      "text": "…っ。調子乗んな。",
      "outfit": "suit"
    },
    {
      "character": "タツ姐",
      "expression": "shy",
      "text": "…でもよ。もっとヤバイことがあって…。",
      "outfit": "suit"
    },
    {
      "character": "player",
      "expression": "closemouth",
      "text": "もっと？"
    },
    {
      "character": "タツ姐",
      "expression": "shy",
      "text": "…お前の声…。予約の電話した時…お前の声聞いたら…。",
      "outfit": "suit"
    },
    {
      "character": "player",
      "expression": "closemouth",
      "text": "声を聞いたら？"
    },
    {
      "character": "タツ姐",
      "expression": "shy",
      "text": "…その場で…下着がダメになった…。声聞いただけで…身体が勝手に…。",
      "outfit": "suit"
    },
    {
      "character": "player",
      "text": "（匂いの次は声か…。五感が次々と俺に支配されていってる…。）"
    },
    {
      "character": "タツ姐",
      "expression": "shy",
      "text": "…先週は匂いだったろ。今度は声だ。…アタシの身体、どうなってんだよ…。",
      "outfit": "suit"
    },
    {
      "character": "player",
      "expression": "closemouth",
      "text": "嗅覚、聴覚…次は何でしょうね。"
    },
    {
      "character": "タツ姐",
      "expression": "angry",
      "text": "楽しそうに言うんじゃねぇ…！",
      "outfit": "suit"
    },
    {
      "character": "タツ姐",
      "expression": "shy",
      "text": "…それでよ…。アタシ、考えたんだ。このままじゃマズイって。",
      "outfit": "suit"
    },
    {
      "character": "player",
      "expression": "closemouth",
      "text": "何か対策を？"
    },
    {
      "character": "タツ姐",
      "expression": "normal",
      "text": "…自分でできるようになれば、ここに来なくて済むと思って…整体の勉強始めた。",
      "outfit": "suit"
    },
    {
      "character": "player",
      "expression": "closemouth",
      "text": "整体の勉強！？ タツ姐さんが？"
    },
    {
      "character": "タツ姐",
      "expression": "normal",
      "text": "ああ。本も買ったし、教材DVDも買った。",
      "outfit": "suit"
    },
    {
      "character": "player",
      "expression": "closemouth",
      "text": "教材DVD？ ちなみに…何ていうシリーズですか？"
    },
    {
      "character": "タツ姐",
      "expression": "normal",
      "text": "えっと…『変態整体師の手技』ってシリーズ。全20巻以上出てて、評判良さそうだったから全巻買った。",
      "outfit": "suit"
    },
    {
      "character": "player",
      "text": "（『変態整体師の手技』…！？ それ…完全にAVじゃん…！！）"
    },
    {
      "character": "player",
      "expression": "closemouth",
      "text": "…タツ姐さん。それ…見たんですか？"
    },
    {
      "character": "タツ姐",
      "expression": "normal",
      "text": "全巻見た。最初は真面目にメモ取りながら見てたんだけどよ…。",
      "outfit": "suit"
    },
    {
      "character": "player",
      "expression": "closemouth",
      "text": "メモ取りながら…。"
    },
    {
      "character": "タツ姐",
      "expression": "shy",
      "text": "…途中から…なんか…様子がおかしくなってきてよ…。",
      "outfit": "suit"
    },
    {
      "character": "player",
      "expression": "closemouth",
      "text": "おかしいって…。"
    },
    {
      "character": "タツ姐",
      "expression": "shy",
      "text": "…………あれ、AVだろ…？",
      "outfit": "suit"
    },
    {
      "character": "player",
      "expression": "closemouth",
      "text": "…タイトルの時点で気づきません…？ 『変態整体師』ですよ…？"
    },
    {
      "character": "タツ姐",
      "expression": "angry",
      "text": "う、うるせぇ！ アタシはそっち方面に疎いんだよ…！ パッケージの女が変な顔してんのも施術が上手すぎるせいだと思ったんだよ…！",
      "outfit": "suit"
    },
    {
      "character": "player",
      "text": "（闇金の社長がAVのパッケージを「施術が上手すぎるせい」って…。純粋すぎる…。）"
    },
    {
      "character": "player",
      "expression": "closemouth",
      "text": "…で、気づいた後はどうしたんですか？"
    },
    {
      "character": "タツ姐",
      "expression": "shy",
      "text": "………………。",
      "outfit": "suit"
    },
    {
      "character": "player",
      "expression": "closemouth",
      "text": "全巻見たって言いましたよね？ 気づいた後も…？"
    },
    {
      "character": "タツ姐",
      "expression": "shy",
      "text": "…………止められなかった……。お前の施術と重ねて見ちまって……。",
      "outfit": "suit"
    },
    {
      "character": "player",
      "text": "（闇金の社長がマッサージAVを全巻鑑賞…。しかもメモ付き…。）"
    },
    {
      "character": "タツ姐",
      "expression": "shy",
      "text": "…見てる間ずっと…身体が熱くて…お前に触られてる気がして…。",
      "outfit": "suit"
    },
    {
      "character": "タツ姐",
      "expression": "angry",
      "text": "…しかもそれだけじゃねぇんだよ…。",
      "outfit": "suit"
    },
    {
      "character": "player",
      "expression": "closemouth",
      "text": "まだ何かあるんですか…？"
    },
    {
      "character": "タツ姐",
      "expression": "shy",
      "text": "…部下がアタシの部屋に書類持ってきた時に…DVDの山と、メモ帳が…机の上に…。",
      "outfit": "suit"
    },
    {
      "character": "player",
      "expression": "closemouth",
      "text": "見られた…？"
    },
    {
      "character": "タツ姐",
      "expression": "shy",
      "text": "『姐さん…この大量のDVD何すか……？ え……変態整体師の……？』って…。",
      "outfit": "suit"
    },
    {
      "character": "player",
      "text": "（部下にマッサージAVの山を見られた闇金の社長…。）"
    },
    {
      "character": "タツ姐",
      "expression": "angry",
      "text": "『教材だ！！ 勉強用だ！！ それ以上聞くな！！』って怒鳴ったけど…絶対信じてねぇ…。",
      "outfit": "suit"
    },
    {
      "character": "player",
      "expression": "closemouth",
      "text": "…信じないでしょうね…。"
    },
    {
      "character": "タツ姐",
      "expression": "shy",
      "text": "…しかもメモ帳に『Vol.7 女子○生への施術が参考になる』って書いてあったのも見られた…。",
      "outfit": "suit"
    },
    {
      "character": "player",
      "text": "（Vol.7…JKモノか…。メモ帳まで見られたのは致命的だな…。）"
    },
    {
      "character": "タツ姐",
      "expression": "angry",
      "text": "次の日から部下の目が…なんか…優しくなった…。「姐さんも色々あるんスね…」みてぇな目で見てきやがる…。",
      "outfit": "suit"
    },
    {
      "character": "player",
      "expression": "closemouth",
      "text": "タツ姐さん…先週のタオル泥棒、柔軟剤調査、今度はAV全巻購入…。毎週スケールが上がってますね…。"
    },
    {
      "character": "タツ姐",
      "expression": "angry",
      "text": "並べんな！！ 全部お前のせいだろうが！！",
      "outfit": "suit"
    },
    {
      "character": "player",
      "expression": "closemouth",
      "text": "…で、結局。自分でやってみてどうだったんですか？ 整体。"
    },
    {
      "character": "タツ姐",
      "expression": "shy",
      "text": "…全然ダメだった。自分で同じとこ押しても…何も感じねぇ…。",
      "outfit": "suit"
    },
    {
      "character": "タツ姐",
      "expression": "shy",
      "text": "…お前の手じゃないと…ダメなんだ……。",
      "outfit": "suit"
    },
    {
      "character": "player",
      "text": "（タオル→柔軟剤→整体の勉強→AV鑑賞→自分で試す→全部失敗→結局俺。…最高のルートだ。）"
    },
    {
      "id": "choice_massage11",
      "character": "player",
      "expression": "closemouth",
      "text": "なるほど…色々頑張ったんですね。",
      "choices": [
        {
          "label": "そこまで努力してくれて嬉しいです",
          "trustDelta": 2,
          "developDelta": 0,
          "next": "trust_path"
        },
        {
          "label": "もう俺から逃げられないですね",
          "trustDelta": 1,
          "developDelta": 2,
          "next": "captive_path"
        },
        {
          "label": "AVで予習済みなら話が早い",
          "trustDelta": 0,
          "developDelta": 3,
          "next": "av_path"
        }
      ]
    },
    {
      "id": "trust_path",
      "character": "player",
      "expression": "closemouth",
      "text": "タオルを持ち帰ったり、柔軟剤を調べたり、整体の勉強までしたり…。そこまでしてくれて、正直嬉しいです。"
    },
    {
      "character": "タツ姐",
      "expression": "shy",
      "text": "…っ。嬉しいって…。別にお前のためにやったんじゃ…。",
      "outfit": "suit"
    },
    {
      "character": "player",
      "expression": "closemouth",
      "text": "でも結局、俺のところに来てくれるんですよね。"
    },
    {
      "character": "タツ姐",
      "expression": "shy",
      "text": "…………ああ。…お前のとこじゃないと…ダメだから…。",
      "outfit": "suit",
      "next": "prepare_massage"
    },
    {
      "id": "captive_path",
      "character": "player",
      "expression": "closemouth",
      "text": "タオルも柔軟剤もDVDも自分の手も、全部ダメだった。もう俺から逃げられないってことですよ。"
    },
    {
      "character": "タツ姐",
      "expression": "angry",
      "text": "逃げるとか…捕まってるわけじゃ…。",
      "outfit": "suit"
    },
    {
      "character": "player",
      "expression": "closemouth",
      "text": "匂いで発情して、声で濡れて、何を試してもダメで、毎週ここに来るしかない。それって完全に捕まってるんじゃないですか？"
    },
    {
      "character": "タツ姐",
      "expression": "shy",
      "text": "…………否定できねぇのがムカつく……。",
      "outfit": "suit",
      "next": "prepare_massage"
    },
    {
      "id": "av_path",
      "character": "player",
      "expression": "closemouth",
      "text": "じゃあ、DVDで予習済みなんですね。今日の施術で何されるか、だいたい分かってるってことだ。"
    },
    {
      "character": "タツ姐",
      "expression": "angry",
      "text": "は…？ お前、あのDVDと同じことする気か…！？",
      "outfit": "suit"
    },
    {
      "character": "player",
      "expression": "closemouth",
      "text": "さぁ、どうでしょうね。タツ姐さん、Vol.7をメモ付きで見たんですよね？ あの巻、どんな施術だったか覚えてます？"
    },
    {
      "character": "タツ姐",
      "expression": "shy",
      "text": "…っ！ あ、あれは…その…。",
      "outfit": "suit"
    },
    {
      "character": "player",
      "expression": "closemouth",
      "text": "全20巻メモ付きで完走した人なら、今から何されるかぜんぶ想像できちゃいますよね。"
    },
    {
      "character": "タツ姐",
      "expression": "shy",
      "text": "…やめろ…想像させんな…もう身体が…。",
      "outfit": "suit"
    },
    {
      "character": "player",
      "expression": "closemouth",
      "text": "DVDの女の人たち、最後どうなってました？"
    },
    {
      "character": "タツ姐",
      "expression": "shy",
      "text": "…っ…………全員…………ぐちゃぐちゃに…されて…た……。",
      "outfit": "suit"
    },
    {
      "character": "player",
      "expression": "closemouth",
      "text": "今日のタツ姐さんも、ああなるかもしれませんね。",
      "next": "prepare_massage"
    },
    {
      "id": "prepare_massage",
      "character": "player",
      "expression": "closemouth",
      "text": "じゃあ、着替えましょうか。"
    },
    {
      "character": "タツ姐",
      "expression": "normal",
      "text": "…ああ。",
      "outfit": "suit"
    },
    {
      "character": "",
      "expression": "closemouth",
      "text": "（タツ姐が着替え始める…）",
      "cutInImage": "tatsu_changing"
    },
    {
      "character": "タツ姐",
      "expression": "shy",
      "text": "（…DVDで見たやつ…全部思い出しちまう…。あの女たち、最初は嫌がってたのに…最後は自分からねだってた…。）",
      "cutInImage": "tatsu_changing"
    },
    {
      "character": "タツ姐",
      "expression": "shy",
      "text": "（…アタシも…同じだ…。最初は嫌だったのに…今はここに来るのが待ち遠しくて…。）",
      "cutInImage": "tatsu_changing"
    },
    {
      "character": "タツ姐",
      "expression": "shy",
      "text": "（…DVDの知識がついたせいで…あいつに何されるか全部わかっちまう…。それが怖いのに…期待してる自分がいる…。）",
      "cutInImage": "tatsu_changing"
    },
    {
      "character": "タツ姐",
      "expression": "shy",
      "text": "（…タオル盗んで、柔軟剤調べて、AV全巻見て…。アタシ、何やってんだ……。闇金の社長が……。）",
      "cutInImage": "tatsu_changing"
    },
    {
      "character": "タツ姐",
      "expression": "normal",
      "text": "…着替えた。",
      "outfit": "bikini"
    },
    {
      "character": "player",
      "text": "（…来た瞬間からもう太ももが光ってる…。DVDの話してる間にずっと興奮してたんだな…。）"
    },
    {
      "character": "player",
      "expression": "closemouth",
      "text": "今日はDVDで予習した分、どこを触られてるかぜんぶ分かっちゃいますね。"
    },
    {
      "character": "タツ姐",
      "expression": "shy",
      "text": "…やめろ…余計なこと言うな…。早く…始めてくれ……。",
      "outfit": "bikini"
    },
    {
      "id": "massage_start",
      "character": "player",
      "expression": "closemouth",
      "text": "はい。それでは…『変態整体師の手技』、実演編を始めましょうか。"
    }
  ]
}
